COPYING
README
setup.py
djabberdjaw/__init__.py
djabberdjaw/manage.py
djabberdjaw/settings.py
djabberdjaw/urls.py
djabberdjaw.egg-info/PKG-INFO
djabberdjaw.egg-info/SOURCES.txt
djabberdjaw.egg-info/dependency_links.txt
djabberdjaw.egg-info/requires.txt
djabberdjaw.egg-info/top_level.txt
djabberdjaw/bot/__init__.py
djabberdjaw/bot/admin.py
djabberdjaw/bot/models.py
djabberdjaw/bot/views.py
djabberdjaw/bot/management/__init__.py
djabberdjaw/bot/management/commands/__init__.py
djabberdjaw/bot/management/commands/runbot.py