Metadata-Version: 1.0
Name: djabberdjaw
Version: 0.1
Summary: A Jabber bot with a Django-backend for user management 
Home-page: http://matienzo.org/project/djabberdjaw
Author: Mark A. Matienzo
Author-email: mark@matienzo.org
License: GPL
Platform: UNKNOWN
Classifier: Intended Audience :: Developers
Classifier: Intended Audience :: Information Technology
Classifier: Framework :: Django
Classifier: License :: OSI Approved :: GNU General Public License (GPL)
Classifier: Programming Language :: Python
Classifier: Development Status :: 3 - Alpha
Classifier: Topic :: Communications :: Chat
